{
  "name": "addison",
  "gender": "female",
  "origin": "English",
  "meaning": "Son of Adam",
  "culturalSignificance": "The name Addison has evolved from its original meaning, 'son of Adam,' to become a popular unisex name, particularly in English-speaking countries. Historically, it was more common as a surname, but over time it has gained popularity as a first name, especially for girls.",
  "modernContext": "Addison has become a trendy name for girls in the United States, often ranking in the top 50 names for baby girls. Its popularity can be attributed to its modern sound and the trend of using surnames as first names.",
  "literaryReferences": "Addison is not widely referenced in classic literature, but it may appear in modern works as a character name due to its contemporary popularity.",
  "pronunciationGuide": "/ˈædɪsən/",
  "variations": [
    "Addyson",
    "Adison",
    "Adyson",
    "Addeson",
    "Addisson",
    "Addysen",
    "Adysson",
    "Adisson",
    "Addisyn"
  ],
  "similarNames": [
    "Madison",
    "Allison",
    "Emerson",
    "Avery",
    "Aubrey",
    "Harper",
    "Peyton",
    "Morgan",
    "Taylor"
  ],
  "nicknames": [
    "Addie",
    "Addy",
    "Adi",
    "Sonny",
    "Didi",
    "Ada",
    "Sisi",
    "Add",
    "Dessa"
  ],
  "personality": "People named Addison are often perceived as creative, outgoing, and independent. They are seen as leaders who are not afraid to take charge and are known for their friendly and approachable nature.",
  "symbolism": "Addison symbolizes modernity and adaptability, reflecting its transition from a traditional surname to a popular first name. It also represents strength and independence.",
  "funFact": "The name Addison gained significant popularity after being used for a character on the TV show 'Grey's Anatomy,' which helped boost its appeal as a first name for girls.",
  "religiousSignificance": {
    "hasSignificance": false,
    "religions": [],
    "character": "",
    "significance": "",
    "keyStories": [],
    "spiritualMeaning": "",
    "historicalImpact": ""
  },
  "historicFigures": [
    {
      "fullName": "Joseph Addison",
      "years": "1672-1719",
      "category": "Writers",
      "achievements": [
        "Co-founder of 'The Spectator' magazine",
        "Renowned essayist and poet"
      ],
      "significance": "Joseph Addison was an influential English essayist, poet, and politician known for his contributions to literature and journalism.",
      "notableWorks": [
        "The Spectator",
        "Cato, a Tragedy"
      ]
    }
  ],
  "famousQuotes": [
    {
      "quote": "Reading is to the mind what exercise is to the body.",
      "author": "Joseph Addison",
      "context": "This quote emphasizes the importance of reading for mental development.",
      "year": 1711,
      "category": "Wisdom"
    }
  ],
  "famousPeople": [
    {
      "name": "Addison Rae",
      "profession": "Social Media Influencer",
      "knownFor": [
        "TikTok videos",
        "Acting in 'He's All That'"
      ],
      "awards": "Nominated for People's Choice Awards"
    }
  ],
  "famousAthletes": [
    {
      "name": "Addison Russell",
      "profession": "Athlete",
      "sport": "MLB Baseball",
      "league": "MLB",
      "team": "Acereros de Monclova",
      "pastTeams": [
        "Chicago Cubs"
      ],
      "position": "Shortstop",
      "jerseyNumber": "27",
      "years": "2015-Present",
      "achievements": "World Series Champion (2016)",
      "knownFor": [
        "Key player in Cubs' 2016 World Series win"
      ],
      "awards": "MLB All-Star (2016)",
      "stats": "Career batting average: .242",
      "verified": true,
      "source": "MLB.com"
    },
    {
      "name": "Addison Reed",
      "profession": "Athlete",
      "sport": "MLB Baseball",
      "league": "MLB",
      "team": "Retired",
      "pastTeams": [
        "Chicago White Sox",
        "Arizona Diamondbacks",
        "New York Mets",
        "Boston Red Sox",
        "Minnesota Twins"
      ],
      "position": "Pitcher",
      "jerseyNumber": "43",
      "years": "2011-2018",
      "achievements": "NL Saves Leader (2013)",
      "knownFor": [
        "Reliable relief pitcher"
      ],
      "awards": "None",
      "stats": "Career ERA: 3.88",
      "verified": true,
      "source": "MLB.com"
    },
    {
      "name": "Addison Gumbs",
      "profession": "Athlete",
      "sport": "American Football (NFL)",
      "league": "NFL",
      "team": "Free Agent",
      "pastTeams": [
        "Oklahoma Sooners (College)",
        "Oregon State Beavers (College)"
      ],
      "position": "Linebacker",
      "jerseyNumber": "N/A",
      "years": "N/A",
      "achievements": "N/A",
      "knownFor": [
        "College football career"
      ],
      "awards": "N/A",
      "stats": "N/A",
      "verified": true,
      "source": "NFL.com"
    }
  ],
  "moviesAndShows": [
    {
      "title": "Grey's Anatomy",
      "year": 2005,
      "type": "TV Show",
      "characterName": "Dr. Addison Montgomery",
      "characterDescription": "A talented neonatal surgeon and OB/GYN",
      "imdbUrl": "https://www.imdb.com/title/tt0413573/",
      "genre": "Drama",
      "verified": true,
      "popularity": 95
    }
  ],
  "characterQuotes": [
    {
      "quote": "We're all damaged, it seems. Some of us more than others.",
      "character": "Dr. Addison Montgomery",
      "source": "Grey's Anatomy",
      "year": 2005,
      "context": "Addison reflects on the personal struggles of herself and her colleagues.",
      "genre": "Drama",
      "impact": "This quote highlights the show's theme of personal and professional challenges."
    }
  ],
  "celestialData": {
    "luckyNumber": 3,
    "dominantElement": "Water",
    "luckyColor": {
      "name": "Golden Yellow",
      "hex": "#FFD700"
    },
    "luckyGemstone": "Topaz",
    "luckyDay": "Thursday",
    "moonPhase": "Waxing Gibbous",
    "moonPhaseDescription": "Period of growth, manifestation, and positive energy.",
    "compatibleSigns": [
      "Aries",
      "Leo",
      "Sagittarius"
    ],
    "compatibleSignsDescription": "Fire signs align with passionate and dynamic energy.",
    "cosmicElement": "Fire",
    "cosmicElementDescription": "Embodies passion, creativity, and transformative power.",
    "celestialArchetype": "The Leader",
    "celestialArchetypeDescription": "Bold, confident, natural leader and pioneer.",
    "karmicLessons": "Embrace courage, develop patience, balance action with reflection",
    "soulUrge": 3,
    "soulUrgeDescription": "Drive for leadership and self-expression"
  },
  "genderDistribution": {
    "male": 5,
    "female": 95
  },
  "ranking": {
    "current": 345,
    "peak": 148,
    "peakYear": 2022
  },
  "enrichmentVersion": "v7",
  "inspiration": null,
  "syllables": {
    "count": 3,
    "breakdown": "addison"
  },
  "translations": [],
  "booksWithName": [],
  "celebrityBabies": [],
  "categories": [
    {
      "tag": "Modern",
      "confidence": 0.85,
      "reason": "Contains 2 modern indicators"
    }
  ],
  "v7EnhancedAt": "2025-11-03T23:34:19.946Z"
}